boiler_simulation/__init__.py
boiler_simulation/simulation.py
tests/__init__.py
tests/test_boiler_simulation.py
boiler_simulation-0.1.0.dist-info/LICENSE
boiler_simulation-0.1.0.dist-info/METADATA
boiler_simulation-0.1.0.dist-info/WHEEL
boiler_simulation-0.1.0.dist-info/entry_points.txt
boiler_simulation-0.1.0.dist-info/top_level.txt
boiler_simulation-0.1.0.dist-info/RECORD
